Workbook

Sheet Simulador
B2: SIMULADOR DE FUNDOS IMOBILIÁRIOS
B4: CONFIGURAÇÕES
B5: Salário mensal (R$) | D5: 2500
B6: Rendimento de dividendos mensal | D6: 0.006
B7: Sugestão de aporte (30%) | D7: =D5*30% -> 750
B8: SIMULAÇÃO
B9: Aporte mensal (R$) | D9: 200
B10: Prazo de investimento (anos) | D10: 5
B11: Rendimento mensal da aplicação | D11: 0.01079
B12: Patrimônio acumulado (R$) | D12: =FV(D11,D10*12,-D9) -> 16755.383
B13: Dividendos mensais (R$) | D13: =D12*D6 -> 100.5323
B14: Prazo (anos)
B15: 2 | C15: =FV($D$11,B15*12,-$D$9) -> 5445.5255 | D15: =C15*$D$6 -> 32.673153
B16: 5 | C16: =FV($D$11,B16*12,-$D$9) -> 16755.383 | D16: =C16*$D$6 -> 100.5323
B17: 10 | C17: =FV($D$11,B17*12,-$D$9) -> 48656.843 | D17: =C17*$D$6 -> 291.94106
B18: 20 | C18: =FV($D$11,B18*12,-$D$9) -> 225039.68 | D18: =C18*$D$6 -> 1350.2381
B19: 30 | C19: =FV($D$11,B19*12,-$D$9) -> 864433.93 | D19: =C19*$D$6 -> 5186.6036
B20: DISTRIBUIÇÃO DO APORTE POR PERFIL
B21: Perfil escolhido | D21: Moderado
B22: Tipo de FII
B23: PAPEL | C23: =VLOOKUP($D$21&"-"&B23,Perfis!$A$2:$D$19,4,FALSE) -> 0.32 | D23: =C23*$D$9 -> 64
B24: TIJOLO | C24: =VLOOKUP($D$21&"-"&B24,Perfis!$A$2:$D$19,4,FALSE) -> 0.35 | D24: =C24*$D$9 -> 70
B25: HÍBRIDOS | C25: =VLOOKUP($D$21&"-"&B25,Perfis!$A$2:$D$19,4,FALSE) -> 0.08 | D25: =C25*$D$9 -> 16
B26: FOFs | C26: =VLOOKUP($D$21&"-"&B26,Perfis!$A$2:$D$19,4,FALSE) -> 0.05 | D26: =C26*$D$9 -> 10
B27: DESENVOLVIMENTO | C27: =VLOOKUP($D$21&"-"&B27,Perfis!$A$2:$D$19,4,FALSE) -> 0.1 | D27: =C27*$D$9 -> 20
B28: HOTELARIAS | C28: =VLOOKUP($D$21&"-"&B28,Perfis!$A$2:$D$19,4,FALSE) -> 0.1 | D28: =C28*$D$9 -> 20
B29: TOTAL | C29: =SUM(C23:C28) -> 1 | D29: =SUM(D23:D28) -> 200

Sheet Perfis
A1: Chave | B1: Perfil | C1: Tipo de FII | D1: Percentual
A2: Conservador-PAPEL | B2: Conservador | C2: PAPEL | D2: 0.3 | F2: Perfil | G2: Soma
A3: Conservador-TIJOLO | B3: Conservador | C3: TIJOLO | D3: 0.5 | F3: Conservador | G3: =SUMIF(B$2:B$19,F3,D$2:D$19) -> 1
A4: Conservador-HÍBRIDOS | B4: Conservador | C4: HÍBRIDOS | D4: 0.1 | F4: Moderado | G4: =SUMIF(B$2:B$19,F4,D$2:D$19) -> 1
A5: Conservador-FOFs | B5: Conservador | C5: FOFs | D5: 0.1 | F5: Agressivo | G5: =SUMIF(B$2:B$19,F5,D$2:D$19) -> 1
A6: Conservador-DESENVOLVIMENTO | B6: Conservador | C6: DESENVOLVIMENTO | D6: 0
A7: Conservador-HOTELARIAS | B7: Conservador | C7: HOTELARIAS | D7: 0
A8: Moderado-PAPEL | B8: Moderado | C8: PAPEL | D8: 0.32
A9: Moderado-TIJOLO | B9: Moderado | C9: TIJOLO | D9: 0.35
A10: Moderado-HÍBRIDOS | B10: Moderado | C10: HÍBRIDOS | D10: 0.08
A11: Moderado-FOFs | B11: Moderado | C11: FOFs | D11: 0.05
A12: Moderado-DESENVOLVIMENTO | B12: Moderado | C12: DESENVOLVIMENTO | D12: 0.1
A13: Moderado-HOTELARIAS | B13: Moderado | C13: HOTELARIAS | D13: 0.1
A14: Agressivo-PAPEL | B14: Agressivo | C14: PAPEL | D14: 0.5
A15: Agressivo-TIJOLO | B15: Agressivo | C15: TIJOLO | D15: 0.1
A16: Agressivo-HÍBRIDOS | B16: Agressivo | C16: HÍBRIDOS | D16: 0.05
A17: Agressivo-FOFs | B17: Agressivo | C17: FOFs | D17: 0.05
... A19: Agressivo-HOTELARIAS | B19: Agressivo | C19: HOTELARIAS | D19: 0.1
